lunchmoney/__init__.py
lunchmoney/api_client.py
lunchmoney/api_response.py
lunchmoney/app.py
lunchmoney/configuration.py
lunchmoney/exceptions.py
lunchmoney/py.typed
lunchmoney/rest.py
lunchmoney/api/__init__.py
lunchmoney/api/categories_api.py
lunchmoney/api/manual_accounts_api.py
lunchmoney/api/me_api.py
lunchmoney/api/plaid_accounts_api.py
lunchmoney/api/recurring_items_api.py
lunchmoney/api/summary_api.py
lunchmoney/api/tags_api.py
lunchmoney/api/transactions_api.py
lunchmoney/api/transactions_bulk_api.py
lunchmoney/api/transactions_files_api.py
lunchmoney/api/transactions_group_api.py
lunchmoney/api/transactions_split_api.py
lunchmoney/models/__init__.py
lunchmoney/models/account_type_enum.py
lunchmoney/models/aligned_category_totals_object.py
lunchmoney/models/aligned_summary_category_object.py
lunchmoney/models/aligned_summary_response_object.py
lunchmoney/models/category_object.py
lunchmoney/models/child_category_object.py
lunchmoney/models/child_transaction_object.py
lunchmoney/models/create_category_request_object.py
lunchmoney/models/create_category_request_object_children_inner.py
lunchmoney/models/create_manual_account_request_object.py
lunchmoney/models/create_manual_account_request_object_balance.py
lunchmoney/models/create_new_transactions_request.py
lunchmoney/models/create_tag_request_object.py
lunchmoney/models/currency_enum.py
lunchmoney/models/delete_category_response_with_dependencies.py
lunchmoney/models/delete_category_response_with_dependencies_dependents.py
lunchmoney/models/delete_tag_response_with_dependencies.py
lunchmoney/models/delete_tag_response_with_dependencies_dependents.py
lunchmoney/models/delete_transactions_request.py
lunchmoney/models/error_response_object.py
lunchmoney/models/error_response_object_errors_inner.py
lunchmoney/models/get_all_categories200_response.py
lunchmoney/models/get_all_manual_accounts200_response.py
lunchmoney/models/get_all_plaid_accounts200_response.py
lunchmoney_python-2.18.2.dist-info/METADATA
lunchmoney_python-2.18.2.dist-info/WHEEL
lunchmoney_python-2.18.2.dist-info/top_level.txt
lunchmoney_python-2.18.2.dist-info/RECORD
