Metadata-Version: 2.4
Name: lunchmoney-python
Version: 2.18.2
Summary: Lunch Money API - v2
Home-page: 
Author: OpenAPI Generator community
Author-email: OpenAPI Generator Community <devsupport@lunchmoney.app>
License: Apache 2.0
Project-URL: Repository, https://github.com/juftin/lunchmoney-clients
Keywords: OpenAPI,OpenAPI-Generator,Lunch Money API - v2
Requires-Python: >=3.9
Requires-Dist: urllib3<3.0.0,>=2.1.0
Requires-Dist: python-dateutil>=2.8.2
Requires-Dist: pydantic>=2
Requires-Dist: typing-extensions>=4.7.1
Dynamic: author
